README.md
setup.cfg
setup.py
dists_udacity_trial/Binomialdistribution.py
dists_udacity_trial/Gaussiandistribution.py
dists_udacity_trial/Generaldistribution.py
dists_udacity_trial/__init__.py
dists_udacity_trial.egg-info/PKG-INFO
dists_udacity_trial.egg-info/SOURCES.txt
dists_udacity_trial.egg-info/dependency_links.txt
dists_udacity_trial.egg-info/not-zip-safe
dists_udacity_trial.egg-info/top_level.txt